odoo8_addon_purchase_order_webkit-8.0.1.0.1-py2.7-nspkg.pth
odoo8_addon_purchase_order_webkit-8.0.1.0.1.dist-info/top_level.txt
odoo8_addon_purchase_order_webkit-8.0.1.0.1.dist-info/WHEEL
odoo8_addon_purchase_order_webkit-8.0.1.0.1.dist-info/RECORD
odoo8_addon_purchase_order_webkit-8.0.1.0.1.dist-info/metadata.json
odoo8_addon_purchase_order_webkit-8.0.1.0.1.dist-info/DESCRIPTION.rst
odoo8_addon_purchase_order_webkit-8.0.1.0.1.dist-info/METADATA
odoo8_addon_purchase_order_webkit-8.0.1.0.1.dist-info/namespace_packages.txt
odoo_addons/purchase_order_webkit/__openerp__.py
odoo_addons/purchase_order_webkit/purchase_report.xml
odoo_addons/purchase_order_webkit/__init__.py
odoo_addons/purchase_order_webkit/report/request_quotation.mako
odoo_addons/purchase_order_webkit/report/purchase_order.mako
odoo_addons/purchase_order_webkit/report/__init__.py
odoo_addons/purchase_order_webkit/view/purchase_view.xml
odoo_addons/purchase_order_webkit/i18n/purchase_order_webkit.pot
odoo_addons/purchase_order_webkit/i18n/de.po
odoo_addons/purchase_order_webkit/i18n/fr.po
